{
	"$schema": "http://schema.management.azure.com/schemas/2015-01-01/deploymentTemplate.json#",
	"contentVersion": "1.0.0.0",
	"parameters": {
		"factoryName": {
			"type": "string",
			"metadata": "Data Factory name",
			"defaultValue": "salesadfmaya"
		},
		"LS_ADLS_accountKey": {
			"type": "secureString",
			"metadata": "Secure string for 'accountKey' of 'LS_ADLS'"
		},
		"LS_AzureKeyVault_properties_typeProperties_baseUrl": {
			"type": "string",
			"defaultValue": "https://valutmayaa.vault.azure.net/"
		},
		"LS_ADLS_properties_typeProperties_url": {
			"type": "string",
			"defaultValue": "https://mayastorageaccco.dfs.core.windows.net/"
		},
		"trigger1_properties_typeProperties_scope": {
			"type": "string",
			"defaultValue": "/subscriptions/fe99f6bb-9115-4d42-a813-a4d0f6c388bf/resourceGroups/bigdatapropject/providers/Microsoft.Storage/storageAccounts/mayastorageaccco"
		}
	},
	"variables": {
		"factoryId": "[concat('Microsoft.DataFactory/factories/', parameters('factoryName'))]"
	},
	"resources": [
		{
			"name": "[concat(parameters('factoryName'), '/LS_AzureKeyVault')]",
			"type": "Microsoft.DataFactory/factories/linkedServices",
			"apiVersion": "2018-06-01",
			"properties": {
				"annotations": [],
				"type": "AzureKeyVault",
				"typeProperties": {
					"baseUrl": "[parameters('LS_AzureKeyVault_properties_typeProperties_baseUrl')]"
				}
			},
			"dependsOn": []
		},
		{
			"name": "[concat(parameters('factoryName'), '/LS_Databricks')]",
			"type": "Microsoft.DataFactory/factories/linkedServices",
			"apiVersion": "2018-06-01",
			"properties": {
				"annotations": [],
				"type": "AzureDatabricks",
				"typeProperties": {
					"domain": "https://adb-1431038938306778.18.azuredatabricks.net",
					"accessToken": {
						"type": "AzureKeyVaultSecret",
						"store": {
							"referenceName": "LS_AzureKeyVault",
							"type": "LinkedServiceReference"
						},
						"secretName": "dababricks-access-token"
					},
					"newClusterNodeType": "Standard_DS3_v2",
					"newClusterNumOfWorker": "1",
					"newClusterSparkEnvVars": {
						"PYSPARK_PYTHON": "/databricks/python3/bin/python3"
					},
					"newClusterVersion": "10.4.x-scala2.12",
					"clusterOption": "Fixed",
					"newClusterInitScripts": []
				}
			},
			"dependsOn": [
				"[concat(variables('factoryId'), '/linkedServices/LS_AzureKeyVault')]"
			]
		},
		{
			"name": "[concat(parameters('factoryName'), '/LS_ADLS')]",
			"type": "Microsoft.DataFactory/factories/linkedServices",
			"apiVersion": "2018-06-01",
			"properties": {
				"annotations": [],
				"type": "AzureBlobFS",
				"typeProperties": {
					"url": "[parameters('LS_ADLS_properties_typeProperties_url')]",
					"accountKey": {
						"type": "SecureString",
						"value": "[parameters('LS_ADLS_accountKey')]"
					}
				}
			},
			"dependsOn": []
		},
		{
			"name": "[concat(parameters('factoryName'), '/pipeline1')]",
			"type": "Microsoft.DataFactory/factories/pipelines",
			"apiVersion": "2018-06-01",
			"properties": {
				"activities": [
					{
						"name": "Notebook1",
						"type": "DatabricksNotebook",
						"dependsOn": [],
						"policy": {
							"timeout": "0.12:00:00",
							"retry": 0,
							"retryIntervalInSeconds": 30,
							"secureOutput": false,
							"secureInput": false
						},
						"userProperties": [],
						"typeProperties": {
							"notebookPath": "/Users/roymaya5679@gmail.com/project1/sales-project"
						},
						"linkedServiceName": {
							"referenceName": "LS_Databricks",
							"type": "LinkedServiceReference"
						}
					}
				],
				"policy": {
					"elapsedTimeMetric": {}
				},
				"annotations": []
			},
			"dependsOn": [
				"[concat(variables('factoryId'), '/linkedServices/LS_Databricks')]"
			]
		},
		{
			"name": "[concat(parameters('factoryName'), '/trigger1')]",
			"type": "Microsoft.DataFactory/factories/triggers",
			"apiVersion": "2018-06-01",
			"properties": {
				"annotations": [],
				"runtimeState": "Started",
				"pipelines": [
					{
						"pipelineReference": {
							"referenceName": "pipeline1",
							"type": "PipelineReference"
						},
						"parameters": {}
					}
				],
				"type": "BlobEventsTrigger",
				"typeProperties": {
					"blobPathBeginsWith": "/sales/blobs/landing",
					"blobPathEndsWith": "orders.csv",
					"ignoreEmptyBlobs": true,
					"scope": "[parameters('trigger1_properties_typeProperties_scope')]",
					"events": [
						"Microsoft.Storage.BlobCreated"
					]
				}
			},
			"dependsOn": [
				"[concat(variables('factoryId'), '/pipelines/pipeline1')]"
			]
		}
	]
}